kcal/__init__.py
kcal/daily_kcal_by_lifestyle.py
kcal/metabolic_rate_prediction.py
percentage_calculators/__init__.py
percentage_calculators/one_rep_max_estimation.py
percentage_calculators/percentage_calculators.py
risk/__init__.py
risk/risk_stratification.py
validation/__init__.py
validation/value_validation.py
exercisecoachtools-0.1.1.dist-info/LICENSE
exercisecoachtools-0.1.1.dist-info/METADATA
exercisecoachtools-0.1.1.dist-info/WHEEL
exercisecoachtools-0.1.1.dist-info/top_level.txt
exercisecoachtools-0.1.1.dist-info/RECORD
