Metadata-Version: 2.1
Name: exercisecoachtools
Version: 0.1.1
Summary: Tools for exercise physiologists and coaches.
Home-page: https://github.com/chandojo/ExerciseCoachTools
Author: chandojo
License: MIT License
Platform: UNKNOWN
Requires-Python: >=3.7, <4
